[
    {
      "docstatus": 0,
      "doctype": "UOM",
      "enabled": 1,
      "modified": "2025-02-15 18:43:30.034046",
      "must_be_whole_number": 0,
      "name": "นิ้ว",
      "uom_name": "นิ้ว"
    },
    {
      "docstatus": 0,
      "doctype": "UOM",
      "enabled": 1,
      "modified": "2025-02-15 18:43:30.034046",
      "must_be_whole_number": 0,
      "name": "ตารางนิ้ว",
      "uom_name": "ตารางนิ้ว"
    },
    {
      "docstatus": 0,
      "doctype": "UOM",
      "enabled": 1,
      "modified": "2025-02-15 18:43:30.034046",
      "must_be_whole_number": 0,
      "name": "ลูกบาศก์นิ้ว",
      "uom_name": "ลูกบาศก์นิ้ว"
    },
    {
      "docstatus": 0,
      "doctype": "UOM",
      "enabled": 1,
      "modified": "2025-02-15 18:43:30.034046",
      "must_be_whole_number": 0,
      "name": "ต่อ mille",
      "uom_name": "ต่อ mille"
    },
    {
      "docstatus": 0,
      "doctype": "UOM",
      "enabled": 1,
      "modified": "2025-02-15 18:43:30.034046",
      "must_be_whole_number": 0,
      "name": "ซีเมนส์ต่อเมตร",
      "uom_name": "ซีเมนส์ต่อเมตร"
    },
    {
      "docstatus": 0,
      "doctype": "UOM",
      "enabled": 1,
      "modified": "2025-02-15 18:43:30.034046",
      "must_be_whole_number": 0,
      "name": "เอเคอร์",
      "uom_name": "เอเคอร์"
    },
    {
      "docstatus": 0,
      "doctype": "UOM",
      "enabled": 1,
      "modified": "2025-02-15 18:43:30.034046",
      "must_be_whole_number": 0,
      "name": "หน่วยนับกิจกรรม",
      "uom_name": "หน่วยนับกิจกรรม"
    },
    {
      "docstatus": 0,
      "doctype": "UOM",
      "enabled": 1,
      "modified": "2025-02-15 18:43:30.034046",
      "must_be_whole_number": 0,
      "name": "ถุง",
      "uom_name": "ถุง"
    },
    {
      "docstatus": 0,
      "doctype": "UOM",
      "enabled": 1,
      "modified": "2025-02-15 18:43:30.034046",
      "must_be_whole_number": 0,
      "name": "เล่ม",
      "uom_name": "เล่ม"
    },
    {
      "docstatus": 0,
      "doctype": "UOM",
      "enabled": 1,
      "modified": "2025-02-15 18:43:30.034046",
      "must_be_whole_number": 0,
      "name": "แกลลอนต่อชั่วโมง",
      "uom_name": "แกลลอนต่อชั่วโมง"
    },
    {
      "docstatus": 0,
      "doctype": "UOM",
      "enabled": 1,
      "modified": "2025-02-15 18:43:30.034046",
      "must_be_whole_number": 0,
      "name": "ขวด",
      "uom_name": "ขวด"
    },
    {
      "docstatus": 0,
      "doctype": "UOM",
      "enabled": 1,
      "modified": "2025-02-15 18:43:30.034046",
      "must_be_whole_number": 0,
      "name": "ลูกบาศก์เซนติเมตร/วินาที",
      "uom_name": "ลูกบาศก์เซนติเมตร/วินาที"
    },
    {
      "docstatus": 0,
      "doctype": "UOM",
      "enabled": 1,
      "modified": "2025-02-15 18:43:30.034046",
      "must_be_whole_number": 0,
      "name": "ตู้",
      "uom_name": "ตู้"
    },
    {
      "docstatus": 0,
      "doctype": "UOM",
      "enabled": 1,
      "modified": "2025-02-15 18:43:30.034046",
      "must_be_whole_number": 0,
      "name": "กระป๋อง",
      "uom_name": "กระป๋อง"
    },
    {
      "docstatus": 0,
      "doctype": "UOM",
      "enabled": 1,
      "modified": "2025-02-15 18:43:30.034046",
      "must_be_whole_number": 0,
      "name": "คัน",
      "uom_name": "คัน"
    },
    {
      "docstatus": 0,
      "doctype": "UOM",
      "enabled": 1,
      "modified": "2025-02-15 18:43:30.034046",
      "must_be_whole_number": 0,
      "name": "ลูกบาศก์เซนติเมตร",
      "uom_name": "ลูกบาศก์เซนติเมตร"
    },
    {
      "docstatus": 0,
      "doctype": "UOM",
      "enabled": 1,
      "modified": "2025-02-15 18:43:30.034046",
      "must_be_whole_number": 0,
      "name": "ลูกบาศก์เดซิเมตร",
      "uom_name": "ลูกบาศก์เดซิเมตร"
    },
    {
      "docstatus": 0,
      "doctype": "UOM",
      "enabled": 1,
      "modified": "2025-02-15 18:43:30.034046",
      "must_be_whole_number": 0,
      "name": "เซนติลิตร",
      "uom_name": "เซนติลิตร"
    },
    {
      "docstatus": 0,
      "doctype": "UOM",
      "enabled": 1,
      "modified": "2025-02-15 18:43:30.034046",
      "must_be_whole_number": 0,
      "name": "เซนติเมตร",
      "uom_name": "เซนติเมตร"
    },
    {
      "docstatus": 0,
      "doctype": "UOM",
      "enabled": 1,
      "modified": "2025-02-15 18:43:30.034046",
      "must_be_whole_number": 0,
      "name": "ตารางเซนติเมตร",
      "uom_name": "ตารางเซนติเมตร"
    },
    {
      "docstatus": 0,
      "doctype": "UOM",
      "enabled": 1,
      "modified": "2025-02-15 18:43:30.034046",
      "must_be_whole_number": 0,
      "name": "เซนติเมตร/วินาที",
      "uom_name": "เซนติเมตร/วินาที"
    },
    {
      "docstatus": 0,
      "doctype": "UOM",
      "enabled": 1,
      "modified": "2025-02-15 18:43:30.034046",
      "must_be_whole_number": 0,
      "name": "กล่อง",
      "uom_name": "กล่อง"
    },
    {
      "docstatus": 0,
      "doctype": "UOM",
      "enabled": 1,
      "modified": "2025-02-15 18:43:30.034046",
      "must_be_whole_number": 0,
      "name": "คาร์ตัน",
      "uom_name": "คาร์ตัน"
    },
    {
      "docstatus": 0,
      "doctype": "UOM",
      "enabled": 1,
      "modified": "2025-02-15 18:43:30.034046",
      "must_be_whole_number": 0,
      "name": "ถ้วย",
      "uom_name": "ถ้วย"
    },
    {
      "docstatus": 0,
      "doctype": "UOM",
      "enabled": 1,
      "modified": "2025-02-15 18:43:30.034046",
      "must_be_whole_number": 0,
      "name": "หีบ",
      "uom_name": "หีบ"
    },
    {
      "docstatus": 0,
      "doctype": "UOM",
      "enabled": 1,
      "modified": "2025-02-15 18:43:30.034046",
      "must_be_whole_number": 0,
      "name": "วัน",
      "uom_name": "วัน"
    },
    {
      "docstatus": 0,
      "doctype": "UOM",
      "enabled": 1,
      "modified": "2025-02-15 18:43:30.034046",
      "must_be_whole_number": 0,
      "name": "องศา",
      "uom_name": "องศา"
    },
    {
      "docstatus": 0,
      "doctype": "UOM",
      "enabled": 1,
      "modified": "2025-02-15 18:43:30.034046",
      "must_be_whole_number": 0,
      "name": "เดซิเมตร",
      "uom_name": "เดซิเมตร"
    },
    {
      "docstatus": 0,
      "doctype": "UOM",
      "enabled": 1,
      "modified": "2025-02-15 18:43:30.034046",
      "must_be_whole_number": 0,
      "name": "ถัง",
      "uom_name": "ถัง"
    },
    {
      "docstatus": 0,
      "doctype": "UOM",
      "enabled": 1,
      "modified": "2025-02-15 18:43:30.034046",
      "must_be_whole_number": 0,
      "name": "โหล",
      "uom_name": "โหล"
    },
    {
      "docstatus": 0,
      "doctype": "UOM",
      "enabled": 1,
      "modified": "2025-02-15 18:43:30.034046",
      "must_be_whole_number": 0,
      "name": "ชิ้น",
      "uom_name": "ชิ้น"
    },
    {
      "docstatus": 0,
      "doctype": "UOM",
      "enabled": 1,
      "modified": "2025-02-15 18:43:30.034046",
      "must_be_whole_number": 0,
      "name": "หน่วยเอมไซน์/มิลลิลิตร",
      "uom_name": "หน่วยเอมไซน์/มิลลิลิตร"
    },
    {
      "docstatus": 0,
      "doctype": "UOM",
      "enabled": 1,
      "modified": "2025-02-15 18:43:30.034046",
      "must_be_whole_number": 0,
      "name": "หน่วยเอมไซน์",
      "uom_name": "หน่วยเอมไซน์"
    },
    {
      "docstatus": 0,
      "doctype": "UOM",
      "enabled": 1,
      "modified": "2025-02-15 18:43:30.034046",
      "must_be_whole_number": 0,
      "name": "แฟ้ม",
      "uom_name": "แฟ้ม"
    },
    {
      "docstatus": 0,
      "doctype": "UOM",
      "enabled": 1,
      "modified": "2025-02-15 18:43:30.034046",
      "must_be_whole_number": 0,
      "name": "ออนซ์หน่วยวัดของเหลว US",
      "uom_name": "ออนซ์หน่วยวัดของเหลว US"
    },
    {
      "docstatus": 0,
      "doctype": "UOM",
      "enabled": 1,
      "modified": "2025-02-15 18:43:30.034046",
      "must_be_whole_number": 0,
      "name": "ฟุต",
      "uom_name": "ฟุต"
    },
    {
      "docstatus": 0,
      "doctype": "UOM",
      "enabled": 1,
      "modified": "2025-02-15 18:43:30.034046",
      "must_be_whole_number": 0,
      "name": "ตารางฟุต",
      "uom_name": "ตารางฟุต"
    },
    {
      "docstatus": 0,
      "doctype": "UOM",
      "enabled": 1,
      "modified": "2025-02-15 18:43:30.034046",
      "must_be_whole_number": 0,
      "name": "ลูกบาศก์ฟุต",
      "uom_name": "ลูกบาศก์ฟุต"
    },
    {
      "docstatus": 0,
      "doctype": "UOM",
      "enabled": 1,
      "modified": "2025-02-15 18:43:30.034046",
      "must_be_whole_number": 0,
      "name": "กิกะจูล",
      "uom_name": "กิกะจูล"
    },
    {
      "docstatus": 0,
      "doctype": "UOM",
      "enabled": 1,
      "modified": "2025-02-15 18:43:30.034046",
      "must_be_whole_number": 0,
      "name": "กรัม",
      "uom_name": "กรัม"
    },
    {
      "docstatus": 0,
      "doctype": "UOM",
      "enabled": 1,
      "modified": "2025-02-15 18:43:30.034046",
      "must_be_whole_number": 0,
      "name": "US แกลลอน",
      "uom_name": "US แกลลอน"
    },
    {
      "docstatus": 0,
      "doctype": "UOM",
      "enabled": 1,
      "modified": "2025-02-15 18:43:30.034046",
      "must_be_whole_number": 0,
      "name": "กรัมทองคำ",
      "uom_name": "กรัมทองคำ"
    },
    {
      "docstatus": 0,
      "doctype": "UOM",
      "enabled": 1,
      "modified": "2025-02-15 18:43:30.034046",
      "must_be_whole_number": 0,
      "name": "gram act.ingrd / liter",
      "uom_name": "gram act.ingrd / liter"
    },
    {
      "docstatus": 0,
      "doctype": "UOM",
      "enabled": 1,
      "modified": "2025-02-15 18:43:30.034046",
      "must_be_whole_number": 0,
      "name": "กรัม/ลิตร",
      "uom_name": "กรัม/ลิตร"
    },
    {
      "docstatus": 0,
      "doctype": "UOM",
      "enabled": 1,
      "modified": "2025-02-15 18:43:30.034046",
      "must_be_whole_number": 0,
      "name": "กรัมต่อโมล",
      "uom_name": "กรัมต่อโมล"
    },
    {
      "docstatus": 0,
      "doctype": "UOM",
      "enabled": 1,
      "modified": "2025-02-15 18:43:30.034046",
      "must_be_whole_number": 0,
      "name": "กรัม/ตารางเมตร",
      "uom_name": "กรัม/ตารางเมตร"
    },
    {
      "docstatus": 0,
      "doctype": "UOM",
      "enabled": 1,
      "modified": "2025-02-15 18:43:30.034046",
      "must_be_whole_number": 0,
      "name": "กรัมต่อลูกบาศก์เมตร",
      "uom_name": "กรัมต่อลูกบาศก์เมตร"
    },
    {
      "docstatus": 0,
      "doctype": "UOM",
      "enabled": 1,
      "modified": "2025-02-15 18:43:30.034046",
      "must_be_whole_number": 0,
      "name": "กิกะโอห์ม",
      "uom_name": "กิกะโอห์ม"
    },
    {
      "docstatus": 0,
      "doctype": "UOM",
      "enabled": 1,
      "modified": "2025-02-15 18:43:30.034046",
      "must_be_whole_number": 0,
      "name": "แกลลอนต่อไมล์",
      "uom_name": "แกลลอนต่อไมล์"
    },
    {
      "docstatus": 0,
      "doctype": "UOM",
      "enabled": 1,
      "modified": "2025-02-15 18:43:30.034046",
      "must_be_whole_number": 0,
      "name": "ตัวใหญ่",
      "uom_name": "ตัวใหญ่"
    },
    {
      "docstatus": 0,
      "doctype": "UOM",
      "enabled": 1,
      "modified": "2025-02-15 18:43:30.034046",
      "must_be_whole_number": 0,
      "name": "กลุ่ม",
      "uom_name": "กลุ่ม"
    },
    {
      "docstatus": 0,
      "doctype": "UOM",
      "enabled": 1,
      "modified": "2025-02-15 18:43:30.034046",
      "must_be_whole_number": 0,
      "name": "ชั่วโมง",
      "uom_name": "ชั่วโมง"
    },
    {
      "docstatus": 0,
      "doctype": "UOM",
      "enabled": 1,
      "modified": "2025-02-15 18:43:30.034046",
      "must_be_whole_number": 0,
      "name": "เฮกตาร์",
      "uom_name": "เฮกตาร์"
    },
    {
      "docstatus": 0,
      "doctype": "UOM",
      "enabled": 1,
      "modified": "2025-02-15 18:43:30.034046",
      "must_be_whole_number": 0,
      "name": "เฮกโตลิตร",
      "uom_name": "เฮกโตลิตร"
    },
    {
      "docstatus": 0,
      "doctype": "UOM",
      "enabled": 1,
      "modified": "2025-02-15 18:43:30.034046",
      "must_be_whole_number": 0,
      "name": "ลูกบาศก์มิลลิเมตร",
      "uom_name": "ลูกบาศก์มิลลิเมตร"
    },
    {
      "docstatus": 0,
      "doctype": "UOM",
      "enabled": 1,
      "modified": "2025-02-15 18:43:30.034046",
      "must_be_whole_number": 0,
      "name": "เมกะนิวตัน",
      "uom_name": "เมกะนิวตัน"
    },
    {
      "docstatus": 0,
      "doctype": "UOM",
      "enabled": 1,
      "modified": "2025-02-15 18:43:30.034046",
      "must_be_whole_number": 0,
      "name": "มิลลินิวตัน/เมตร",
      "uom_name": "มิลลินิวตัน/เมตร"
    },
    {
      "docstatus": 0,
      "doctype": "UOM",
      "enabled": 1,
      "modified": "2025-02-15 18:43:30.034046",
      "must_be_whole_number": 0,
      "name": "ไมล์ต่อแกลลอน",
      "uom_name": "ไมล์ต่อแกลลอน"
    },
    {
      "docstatus": 0,
      "doctype": "UOM",
      "enabled": 1,
      "modified": "2025-02-15 18:43:30.034046",
      "must_be_whole_number": 0,
      "name": "มิลิโมลต่อลิตร",
      "uom_name": "มิลิโมลต่อลิตร"
    },
    {
      "docstatus": 0,
      "doctype": "UOM",
      "enabled": 1,
      "modified": "2025-02-15 18:43:30.034046",
      "must_be_whole_number": 0,
      "name": "มิลลิปาสคาลวินาที",
      "uom_name": "มิลลิปาสคาลวินาที"
    },
    {
      "docstatus": 0,
      "doctype": "UOM",
      "enabled": 1,
      "modified": "2025-02-15 18:43:30.034046",
      "must_be_whole_number": 0,
      "name": "พิโควินาที",
      "uom_name": "พิโควินาที"
    },
    {
      "docstatus": 0,
      "doctype": "UOM",
      "enabled": 1,
      "modified": "2025-02-15 18:43:30.034046",
      "must_be_whole_number": 0,
      "name": "เมตร/วินาทีกำลังสอง",
      "uom_name": "เมตร/วินาทีกำลังสอง"
    },
    {
      "docstatus": 0,
      "doctype": "UOM",
      "enabled": 1,
      "modified": "2025-02-15 18:43:30.034046",
      "must_be_whole_number": 0,
      "name": "ไมโครซเมนส์ต่อเซนติเมตร",
      "uom_name": "ไมโครซเมนส์ต่อเซนติเมตร"
    },
    {
      "docstatus": 0,
      "doctype": "UOM",
      "enabled": 1,
      "modified": "2025-02-15 18:43:30.034046",
      "must_be_whole_number": 0,
      "name": "มิลลิวินาที",
      "uom_name": "มิลลิวินาที"
    },
    {
      "docstatus": 0,
      "doctype": "UOM",
      "enabled": 1,
      "modified": "2025-02-15 18:43:30.034046",
      "must_be_whole_number": 0,
      "name": "เดือน",
      "uom_name": "เดือน"
    },
    {
      "docstatus": 0,
      "doctype": "UOM",
      "enabled": 1,
      "modified": "2025-02-15 18:43:30.034046",
      "must_be_whole_number": 0,
      "name": "เมกะวัตต์ ชั่วโมง",
      "uom_name": "เมกะวัตต์ ชั่วโมง"
    },
    {
      "docstatus": 0,
      "doctype": "UOM",
      "enabled": 1,
      "modified": "2025-02-15 18:43:30.034046",
      "must_be_whole_number": 0,
      "name": "นาโนแอมแปร์",
      "uom_name": "นาโนแอมแปร์"
    },
    {
      "docstatus": 0,
      "doctype": "UOM",
      "enabled": 1,
      "modified": "2025-02-15 18:43:30.034046",
      "must_be_whole_number": 0,
      "name": "นาโนเมตร",
      "uom_name": "นาโนเมตร"
    },
    {
      "docstatus": 0,
      "doctype": "UOM",
      "enabled": 1,
      "modified": "2025-02-15 18:43:30.034046",
      "must_be_whole_number": 0,
      "name": "Gram act. ingrd.",
      "uom_name": "Gram act. ingrd."
    },
    {
      "docstatus": 0,
      "doctype": "UOM",
      "enabled": 1,
      "modified": "2025-02-15 18:43:30.034046",
      "must_be_whole_number": 0,
      "name": "กิโลนิวตัน",
      "uom_name": "กิโลนิวตัน"
    },
    {
      "docstatus": 0,
      "doctype": "UOM",
      "enabled": 1,
      "modified": "2025-02-15 18:43:30.034046",
      "must_be_whole_number": 0,
      "name": "นิวตัน/เมตร",
      "uom_name": "นิวตัน/เมตร"
    },
    {
      "docstatus": 0,
      "doctype": "UOM",
      "enabled": 1,
      "modified": "2025-02-15 18:43:30.034046",
      "must_be_whole_number": 0,
      "name": "นิวตัน/ตารางมิลลิเมตร",
      "uom_name": "นิวตัน/ตารางมิลลิเมตร"
    },
    {
      "docstatus": 0,
      "doctype": "UOM",
      "enabled": 1,
      "modified": "2025-02-15 18:43:30.034046",
      "must_be_whole_number": 0,
      "name": "นาโนวินาที",
      "uom_name": "นาโนวินาที"
    },
    {
      "docstatus": 0,
      "doctype": "UOM",
      "enabled": 1,
      "modified": "2025-02-15 18:43:30.034046",
      "must_be_whole_number": 0,
      "name": "ออนซ์",
      "uom_name": "ออนซ์"
    },
    {
      "docstatus": 0,
      "doctype": "UOM",
      "enabled": 1,
      "modified": "2025-02-15 18:43:30.034046",
      "must_be_whole_number": 0,
      "name": "จุด",
      "uom_name": "จุด"
    },
    {
      "docstatus": 0,
      "doctype": "UOM",
      "enabled": 1,
      "modified": "2025-02-15 18:43:30.034046",
      "must_be_whole_number": 0,
      "name": "คู่",
      "uom_name": "คู่"
    },
    {
      "docstatus": 0,
      "doctype": "UOM",
      "enabled": 1,
      "modified": "2025-02-15 18:43:30.034046",
      "must_be_whole_number": 0,
      "name": "แพค/ห่อ",
      "uom_name": "แพค/ห่อ"
    },
    {
      "docstatus": 0,
      "doctype": "UOM",
      "enabled": 1,
      "modified": "2025-02-15 18:43:30.034046",
      "must_be_whole_number": 0,
      "name": "แพลเลต",
      "uom_name": "แพลเลต"
    },
    {
      "docstatus": 0,
      "doctype": "UOM",
      "enabled": 1,
      "modified": "2025-02-15 18:43:30.034046",
      "must_be_whole_number": 0,
      "name": "ปาสคาลวินาที",
      "uom_name": "ปาสคาลวินาที"
    },
    {
      "docstatus": 0,
      "doctype": "UOM",
      "enabled": 1,
      "modified": "2025-02-15 18:43:30.034046",
      "must_be_whole_number": 0,
      "name": "เมกะโวลต์แอมแปร์",
      "uom_name": "เมกะโวลต์แอมแปร์"
    },
    {
      "docstatus": 0,
      "doctype": "UOM",
      "enabled": 1,
      "modified": "2025-02-15 18:43:30.034046",
      "must_be_whole_number": 0,
      "name": "กิโลกรัมต่อลูกบาศก์เมตร",
      "uom_name": "กิโลกรัมต่อลูกบาศก์เมตร"
    },
    {
      "docstatus": 0,
      "doctype": "UOM",
      "enabled": 1,
      "modified": "2025-02-15 18:43:30.034046",
      "must_be_whole_number": 0,
      "name": "หนึ่ง/นาที",
      "uom_name": "หนึ่ง/นาที"
    },
    {
      "docstatus": 0,
      "doctype": "UOM",
      "enabled": 1,
      "modified": "2025-02-15 18:43:30.034046",
      "must_be_whole_number": 0,
      "name": "อัตราส่วนพันล้าน",
      "uom_name": "อัตราส่วนพันล้าน"
    },
    {
      "docstatus": 0,
      "doctype": "UOM",
      "enabled": 1,
      "modified": "2025-02-15 18:43:30.034046",
      "must_be_whole_number": 0,
      "name": "อัตราส่วนล้าน",
      "uom_name": "อัตราส่วนล้าน"
    },
    {
      "docstatus": 0,
      "doctype": "UOM",
      "enabled": 1,
      "modified": "2025-02-15 18:43:30.034046",
      "must_be_whole_number": 0,
      "name": "อัตราส่วนล้านล้าน",
      "uom_name": "อัตราส่วนล้านล้าน"
    },
    {
      "docstatus": 0,
      "doctype": "UOM",
      "enabled": 1,
      "modified": "2025-02-15 18:43:30.034046",
      "must_be_whole_number": 0,
      "name": "งวด",
      "uom_name": "งวด"
    },
    {
      "docstatus": 0,
      "doctype": "UOM",
      "enabled": 1,
      "modified": "2025-02-15 18:43:30.034046",
      "must_be_whole_number": 0,
      "name": "คน",
      "uom_name": "คน"
    },
    {
      "docstatus": 0,
      "doctype": "UOM",
      "enabled": 1,
      "modified": "2025-02-15 18:43:30.034046",
      "must_be_whole_number": 0,
      "name": "ไพนท์",
      "uom_name": "ไพนท์"
    },
    {
      "docstatus": 0,
      "doctype": "UOM",
      "enabled": 1,
      "modified": "2025-02-15 18:43:30.034046",
      "must_be_whole_number": 0,
      "name": "กิโลโมล",
      "uom_name": "กิโลโมล"
    },
    {
      "docstatus": 0,
      "doctype": "UOM",
      "enabled": 1,
      "modified": "2025-02-15 18:43:30.034046",
      "must_be_whole_number": 0,
      "name": "ควอรท",
      "uom_name": "ควอรท"
    },
    {
      "docstatus": 0,
      "doctype": "UOM",
      "enabled": 1,
      "modified": "2025-02-15 18:43:30.034046",
      "must_be_whole_number": 0,
      "name": "มิลลิฟาเรด",
      "uom_name": "มิลลิฟาเรด"
    },
    {
      "docstatus": 0,
      "doctype": "UOM",
      "enabled": 1,
      "modified": "2025-02-15 18:43:30.034046",
      "must_be_whole_number": 0,
      "name": "กรัม/ลูกบาศก์เซนติเมตร",
      "uom_name": "กรัม/ลูกบาศก์เซนติเมตร"
    },
    {
      "docstatus": 0,
      "doctype": "UOM",
      "enabled": 1,
      "modified": "2025-02-15 18:43:30.034046",
      "must_be_whole_number": 0,
      "name": "รีม",
      "uom_name": "รีม"
    },
    {
      "docstatus": 0,
      "doctype": "UOM",
      "enabled": 1,
      "modified": "2025-02-15 18:43:30.034046",
      "must_be_whole_number": 0,
      "name": "Roll",
      "uom_name": "Roll"
    },
    {
      "docstatus": 0,
      "doctype": "UOM",
      "enabled": 1,
      "modified": "2025-02-15 18:43:30.034046",
      "must_be_whole_number": 0,
      "name": "นาโนฟาเรด",
      "uom_name": "นาโนฟาเรด"
    },
    {
      "docstatus": 0,
      "doctype": "UOM",
      "enabled": 1,
      "modified": "2025-02-15 18:43:30.034046",
      "must_be_whole_number": 0,
      "name": "ผืน",
      "uom_name": "ผืน"
    },
    {
      "docstatus": 0,
      "doctype": "UOM",
      "enabled": 1,
      "modified": "2025-02-15 18:43:30.034046",
      "must_be_whole_number": 0,
      "name": "แผ่น",
      "uom_name": "แผ่น"
    },
    {
      "docstatus": 0,
      "doctype": "UOM",
      "enabled": 1,
      "modified": "2025-02-15 18:43:30.034046",
      "must_be_whole_number": 0,
      "name": "ชุด",
      "uom_name": "ชุด"
    },
    {
      "docstatus": 0,
      "doctype": "UOM",
      "enabled": 1,
      "modified": "2025-02-15 18:43:30.034046",
      "must_be_whole_number": 0,
      "name": "ท่อน",
      "uom_name": "ท่อน"
    },
    {
      "docstatus": 0,
      "doctype": "UOM",
      "enabled": 1,
      "modified": "2025-02-15 18:43:30.034046",
      "must_be_whole_number": 0,
      "name": "ระบบ",
      "uom_name": "ระบบ"
    },
    {
      "docstatus": 0,
      "doctype": "UOM",
      "enabled": 1,
      "modified": "2025-02-15 18:43:30.034046",
      "must_be_whole_number": 0,
      "name": "หลักพัน",
      "uom_name": "หลักพัน"
    },
    {
      "docstatus": 0,
      "doctype": "UOM",
      "enabled": 1,
      "modified": "2025-02-15 18:43:30.034046",
      "must_be_whole_number": 0,
      "name": "ครั้ง",
      "uom_name": "ครั้ง"
    },
    {
      "docstatus": 0,
      "doctype": "UOM",
      "enabled": 1,
      "modified": "2025-02-15 18:43:30.034046",
      "must_be_whole_number": 0,
      "name": "ตัน",
      "uom_name": "ตัน"
    },
    {
      "docstatus": 0,
      "doctype": "UOM",
      "enabled": 1,
      "modified": "2025-02-15 18:43:30.034046",
      "must_be_whole_number": 0,
      "name": "ชั่วโมง",
      "uom_name": "ชั่วโมง"
    },
    {
      "docstatus": 0,
      "doctype": "UOM",
      "enabled": 1,
      "modified": "2025-02-15 18:43:30.034046",
      "must_be_whole_number": 0,
      "name": "พิโคฟาเรด",
      "uom_name": "พิโคฟาเรด"
    },
    {
      "docstatus": 0,
      "doctype": "UOM",
      "enabled": 1,
      "modified": "2025-02-15 18:43:30.034046",
      "must_be_whole_number": 0,
      "name": "จูล/กิโลกรัม",
      "uom_name": "จูล/กิโลกรัม"
    },
    {
      "docstatus": 0,
      "doctype": "UOM",
      "enabled": 1,
      "modified": "2025-02-15 18:43:30.034046",
      "must_be_whole_number": 0,
      "name": "จูล/โมล",
      "uom_name": "จูล/โมล"
    },
    {
      "docstatus": 0,
      "doctype": "UOM",
      "enabled": 1,
      "modified": "2025-02-15 18:43:30.034046",
      "must_be_whole_number": 0,
      "name": "งาน",
      "uom_name": "งาน"
    },
    {
      "docstatus": 0,
      "doctype": "UOM",
      "enabled": 1,
      "modified": "2025-02-15 18:43:30.034046",
      "must_be_whole_number": 0,
      "name": "Kilogram act. ingrd.",
      "uom_name": "Kilogram act. ingrd."
    },
    {
      "docstatus": 0,
      "doctype": "UOM",
      "enabled": 1,
      "modified": "2025-02-15 18:43:30.034046",
      "must_be_whole_number": 0,
      "name": "กิโลกรัมต่อลูกบาศก์เดซิเมตร",
      "uom_name": "กิโลกรัมต่อลูกบาศก์เดซิเมตร"
    },
    {
      "docstatus": 0,
      "doctype": "UOM",
      "enabled": 1,
      "modified": "2025-02-15 18:43:30.034046",
      "must_be_whole_number": 0,
      "name": "กิโลกรัม",
      "uom_name": "กิโลกรัม"
    },
    {
      "docstatus": 0,
      "doctype": "UOM",
      "enabled": 1,
      "modified": "2025-02-15 18:43:30.034046",
      "must_be_whole_number": 0,
      "name": "กิโลกรัม/โมล",
      "uom_name": "กิโลกรัม/โมล"
    },
    {
      "docstatus": 0,
      "doctype": "UOM",
      "enabled": 1,
      "modified": "2025-02-15 18:43:30.034046",
      "must_be_whole_number": 0,
      "name": "กิโลกรัมต่อวินาที",
      "uom_name": "กิโลกรัมต่อวินาที"
    },
    {
      "docstatus": 0,
      "doctype": "UOM",
      "enabled": 1,
      "modified": "2025-02-15 18:43:30.034046",
      "must_be_whole_number": 0,
      "name": "kg act.ingrd. / kg",
      "uom_name": "kg act.ingrd. / kg"
    },
    {
      "docstatus": 0,
      "doctype": "UOM",
      "enabled": 1,
      "modified": "2025-02-15 18:43:30.034046",
      "must_be_whole_number": 0,
      "name": "กิโลจูล/กิโลกรัม",
      "uom_name": "กิโลจูล/กิโลกรัม"
    },
    {
      "docstatus": 0,
      "doctype": "UOM",
      "enabled": 1,
      "modified": "2025-02-15 18:43:30.034046",
      "must_be_whole_number": 0,
      "name": "กิโลจูล/โมล",
      "uom_name": "กิโลจูล/โมล"
    },
    {
      "docstatus": 0,
      "doctype": "UOM",
      "enabled": 1,
      "modified": "2025-02-15 18:43:30.034046",
      "must_be_whole_number": 0,
      "name": "กิโลเมตร",
      "uom_name": "กิโลเมตร"
    },
    {
      "docstatus": 0,
      "doctype": "UOM",
      "enabled": 1,
      "modified": "2025-02-15 18:43:30.034046",
      "must_be_whole_number": 0,
      "name": "ตารางกิโลเมตร",
      "uom_name": "ตารางกิโลเมตร"
    },
    {
      "docstatus": 0,
      "doctype": "UOM",
      "enabled": 1,
      "modified": "2025-02-15 18:43:30.034046",
      "must_be_whole_number": 0,
      "name": "กิโลเมตรต่อชั่วโมง",
      "uom_name": "กิโลเมตรต่อชั่วโมง"
    },
    {
      "docstatus": 0,
      "doctype": "UOM",
      "enabled": 1,
      "modified": "2025-02-15 18:43:30.034046",
      "must_be_whole_number": 0,
      "name": "เคลวิน/นาที",
      "uom_name": "เคลวิน/นาที"
    },
    {
      "docstatus": 0,
      "doctype": "UOM",
      "enabled": 1,
      "modified": "2025-02-15 18:43:30.034046",
      "must_be_whole_number": 0,
      "name": "เคลวิน/วินาที",
      "uom_name": "เคลวิน/วินาที"
    },
    {
      "docstatus": 0,
      "doctype": "UOM",
      "enabled": 1,
      "modified": "2025-02-15 18:43:30.034046",
      "must_be_whole_number": 0,
      "name": "กิโลปาสคาล",
      "uom_name": "กิโลปาสคาล"
    },
    {
      "docstatus": 0,
      "doctype": "UOM",
      "enabled": 1,
      "modified": "2025-02-15 18:43:30.034046",
      "must_be_whole_number": 0,
      "name": "กิโลโวลต์แอมแปร์",
      "uom_name": "กิโลโวลต์แอมแปร์"
    },
    {
      "docstatus": 0,
      "doctype": "UOM",
      "enabled": 1,
      "modified": "2025-02-15 18:43:30.034046",
      "must_be_whole_number": 0,
      "name": "ลิตร",
      "uom_name": "ลิตร"
    },
    {
      "docstatus": 0,
      "doctype": "UOM",
      "enabled": 1,
      "modified": "2025-02-15 18:43:30.034046",
      "must_be_whole_number": 0,
      "name": "US ปอนด์",
      "uom_name": "US ปอนด์"
    },
    {
      "docstatus": 0,
      "doctype": "UOM",
      "enabled": 1,
      "modified": "2025-02-15 18:43:30.034046",
      "must_be_whole_number": 0,
      "name": "ลิตรต่อ 100 กิโลเมตร",
      "uom_name": "ลิตรต่อ 100 กิโลเมตร"
    },
    {
      "docstatus": 0,
      "doctype": "UOM",
      "enabled": 1,
      "modified": "2025-02-15 18:43:30.034046",
      "must_be_whole_number": 0,
      "name": "ลิตร/นาที",
      "uom_name": "ลิตร/นาที"
    },
    {
      "docstatus": 0,
      "doctype": "UOM",
      "enabled": 1,
      "modified": "2025-02-15 18:43:30.034046",
      "must_be_whole_number": 0,
      "name": "ลิตร/โมลวินาที",
      "uom_name": "ลิตร/โมลวินาที"
    },
    {
      "docstatus": 0,
      "doctype": "UOM",
      "enabled": 1,
      "modified": "2025-02-15 18:43:30.034046",
      "must_be_whole_number": 0,
      "name": "ลิตรต่อชั่วโมง",
      "uom_name": "ลิตรต่อชั่วโมง"
    },
    {
      "docstatus": 0,
      "doctype": "UOM",
      "enabled": 1,
      "modified": "2025-02-15 18:43:30.034046",
      "must_be_whole_number": 0,
      "name": "Kilotonne",
      "uom_name": "Kilotonne"
    },
    {
      "docstatus": 0,
      "doctype": "UOM",
      "enabled": 1,
      "modified": "2025-02-15 18:43:30.034046",
      "must_be_whole_number": 0,
      "name": "เมตร",
      "uom_name": "เมตร"
    },
    {
      "docstatus": 0,
      "doctype": "UOM",
      "enabled": 1,
      "modified": "2025-02-15 18:43:30.034046",
      "must_be_whole_number": 0,
      "name": "โมลต่อลิตร",
      "uom_name": "โมลต่อลิตร"
    },
    {
      "docstatus": 0,
      "doctype": "UOM",
      "enabled": 1,
      "modified": "2025-02-15 18:43:30.034046",
      "must_be_whole_number": 0,
      "name": "โมลต่อลูกบาศก์เมตร",
      "uom_name": "โมลต่อลูกบาศก์เมตร"
    },
    {
      "docstatus": 0,
      "doctype": "UOM",
      "enabled": 1,
      "modified": "2025-02-15 18:43:30.034046",
      "must_be_whole_number": 0,
      "name": "เมตร/วินาที",
      "uom_name": "เมตร/วินาที"
    },
    {
      "docstatus": 0,
      "doctype": "UOM",
      "enabled": 1,
      "modified": "2025-02-15 18:43:30.034046",
      "must_be_whole_number": 0,
      "name": "ตารางเมตร",
      "uom_name": "ตารางเมตร"
    },
    {
      "docstatus": 0,
      "doctype": "UOM",
      "enabled": 1,
      "modified": "2025-02-15 18:43:30.034046",
      "must_be_whole_number": 0,
      "name": "1 / ตารางเมตร",
      "uom_name": "1 / ตารางเมตร"
    },
    {
      "docstatus": 0,
      "doctype": "UOM",
      "enabled": 1,
      "modified": "2025-02-15 18:43:30.034046",
      "must_be_whole_number": 0,
      "name": "ตารางเมตร/วินาที",
      "uom_name": "ตารางเมตร/วินาที"
    },
    {
      "docstatus": 0,
      "doctype": "UOM",
      "enabled": 1,
      "modified": "2025-02-15 18:43:30.034046",
      "must_be_whole_number": 0,
      "name": "ลูกบาศก์เมตร",
      "uom_name": "ลูกบาศก์เมตร"
    },
    {
      "docstatus": 0,
      "doctype": "UOM",
      "enabled": 1,
      "modified": "2025-02-15 18:43:30.034046",
      "must_be_whole_number": 0,
      "name": "ลูกบาศก์เมตร/ชั่วโมง",
      "uom_name": "ลูกบาศก์เมตร/ชั่วโมง"
    },
    {
      "docstatus": 0,
      "doctype": "UOM",
      "enabled": 1,
      "modified": "2025-02-15 18:43:30.034046",
      "must_be_whole_number": 0,
      "name": "ลูกบาศก์เมตร/วินาที",
      "uom_name": "ลูกบาศก์เมตร/วินาที"
    },
    {
      "docstatus": 0,
      "doctype": "UOM",
      "enabled": 1,
      "modified": "2025-02-15 18:43:30.034046",
      "must_be_whole_number": 0,
      "name": "เครื่อง",
      "uom_name": "เครื่อง"
    },
    {
      "docstatus": 0,
      "doctype": "UOM",
      "enabled": 1,
      "modified": "2025-02-15 18:43:30.034046",
      "must_be_whole_number": 0,
      "name": "มัด",
      "uom_name": "มัด"
    },
    {
      "docstatus": 0,
      "doctype": "UOM",
      "enabled": 1,
      "modified": "2025-02-15 18:43:30.034046",
      "must_be_whole_number": 0,
      "name": "เมกะจูล",
      "uom_name": "เมกะจูล"
    },
    {
      "docstatus": 0,
      "doctype": "UOM",
      "enabled": 1,
      "modified": "2025-02-15 18:43:30.034046",
      "must_be_whole_number": 0,
      "name": "มิลลิกรัม",
      "uom_name": "มิลลิกรัม"
    },
    {
      "docstatus": 0,
      "doctype": "UOM",
      "enabled": 1,
      "modified": "2025-02-15 18:43:30.034046",
      "must_be_whole_number": 0,
      "name": "มิลลิกรัม/ลิตร",
      "uom_name": "มิลลิกรัม/ลิตร"
    },
    {
      "docstatus": 0,
      "doctype": "UOM",
      "enabled": 1,
      "modified": "2025-02-15 18:43:30.034046",
      "must_be_whole_number": 0,
      "name": "เมกะโอมห์",
      "uom_name": "เมกะโอมห์"
    },
    {
      "docstatus": 0,
      "doctype": "UOM",
      "enabled": 1,
      "modified": "2025-02-15 18:43:30.034046",
      "must_be_whole_number": 0,
      "name": "มิลลิกรัม/ลูกบาศก์เมตร",
      "uom_name": "มิลลิกรัม/ลูกบาศก์เมตร"
    },
    {
      "docstatus": 0,
      "doctype": "UOM",
      "enabled": 1,
      "modified": "2025-02-15 18:43:30.034046",
      "must_be_whole_number": 0,
      "name": "เมตร/ชั่วโมง",
      "uom_name": "เมตร/ชั่วโมง"
    },
    {
      "docstatus": 0,
      "doctype": "UOM",
      "enabled": 1,
      "modified": "2025-02-15 18:43:30.034046",
      "must_be_whole_number": 0,
      "name": "เมกะโวลต์",
      "uom_name": "เมกะโวลต์"
    },
    {
      "docstatus": 0,
      "doctype": "UOM",
      "enabled": 1,
      "modified": "2025-02-15 18:43:30.034046",
      "must_be_whole_number": 0,
      "name": "ไมล์",
      "uom_name": "ไมล์"
    },
    {
      "docstatus": 0,
      "doctype": "UOM",
      "enabled": 1,
      "modified": "2025-02-15 18:43:30.034046",
      "must_be_whole_number": 0,
      "name": "ตารางไมล์",
      "uom_name": "ตารางไมล์"
    },
    {
      "docstatus": 0,
      "doctype": "UOM",
      "enabled": 1,
      "modified": "2025-02-15 18:43:30.034046",
      "must_be_whole_number": 0,
      "name": "นาที",
      "uom_name": "นาที"
    },
    {
      "docstatus": 0,
      "doctype": "UOM",
      "enabled": 1,
      "modified": "2025-02-15 18:43:30.034046",
      "must_be_whole_number": 0,
      "name": "ไมโครวินาที",
      "uom_name": "ไมโครวินาที"
    },
    {
      "docstatus": 0,
      "doctype": "UOM",
      "enabled": 1,
      "modified": "2025-02-15 18:43:30.034046",
      "must_be_whole_number": 0,
      "name": "มิลลิลิตร",
      "uom_name": "มิลลิลิตร"
    },
    {
      "docstatus": 0,
      "doctype": "UOM",
      "enabled": 1,
      "modified": "2025-02-15 18:43:30.034046",
      "must_be_whole_number": 0,
      "name": "Milliliter act. ingr.",
      "uom_name": "Milliliter act. ingr."
    },
    {
      "docstatus": 0,
      "doctype": "UOM",
      "enabled": 1,
      "modified": "2025-02-15 18:43:30.034046",
      "must_be_whole_number": 0,
      "name": "มิลลิเมตร",
      "uom_name": "มิลลิเมตร"
    },
    {
      "docstatus": 0,
      "doctype": "UOM",
      "enabled": 1,
      "modified": "2025-02-15 18:43:30.034046",
      "must_be_whole_number": 0,
      "name": "ตารางมิลลิเมตร",
      "uom_name": "ตารางมิลลิเมตร"
    },
    {
      "docstatus": 0,
      "doctype": "UOM",
      "enabled": 1,
      "modified": "2025-02-15 18:43:30.034046",
      "must_be_whole_number": 0,
      "name": "ตัน/ลูกบาศก์เมตร",
      "uom_name": "ตัน/ลูกบาศก์เมตร"
    },
    {
      "docstatus": 0,
      "doctype": "UOM",
      "enabled": 1,
      "modified": "2025-02-15 18:43:30.034046",
      "must_be_whole_number": 0,
      "name": "US ตัน",
      "uom_name": "US ตัน"
    },
    {
      "docstatus": 0,
      "doctype": "UOM",
      "enabled": 1,
      "modified": "2025-02-15 18:43:30.034046",
      "must_be_whole_number": 0,
      "name": "ท่อ",
      "uom_name": "ท่อ"
    },
    {
      "docstatus": 0,
      "doctype": "UOM",
      "enabled": 1,
      "modified": "2025-02-15 18:43:30.034046",
      "must_be_whole_number": 0,
      "name": "แท่ง",
      "uom_name": "แท่ง"
    },
    {
      "docstatus": 0,
      "doctype": "UOM",
      "enabled": 1,
      "modified": "2025-02-15 18:43:30.034046",
      "must_be_whole_number": 0,
      "name": "ขด",
      "uom_name": "ขด"
    },
    {
      "docstatus": 0,
      "doctype": "UOM",
      "enabled": 1,
      "modified": "2025-02-15 18:43:30.034046",
      "must_be_whole_number": 0,
      "name": "โคม",
      "uom_name": "โคม"
    },
    {
      "docstatus": 0,
      "doctype": "UOM",
      "enabled": 1,
      "modified": "2025-02-15 18:43:30.034046",
      "must_be_whole_number": 0,
      "name": "คิว",
      "uom_name": "คิว"
    },
    {
      "docstatus": 0,
      "doctype": "UOM",
      "enabled": 1,
      "modified": "2025-02-15 18:43:30.034046",
      "must_be_whole_number": 0,
      "name": "ปี๊บ",
      "uom_name": "ปี๊บ"
    },
    {
      "docstatus": 0,
      "doctype": "UOM",
      "enabled": 1,
      "modified": "2025-02-15 18:43:30.034046",
      "must_be_whole_number": 0,
      "name": "ซอง",
      "uom_name": "ซอง"
    },
    {
      "docstatus": 0,
      "doctype": "UOM",
      "enabled": 1,
      "modified": "2025-02-15 18:43:30.034046",
      "must_be_whole_number": 0,
      "name": "ดวง",
      "uom_name": "ดวง"
    },
    {
      "docstatus": 0,
      "doctype": "UOM",
      "enabled": 1,
      "modified": "2025-02-15 18:43:30.034046",
      "must_be_whole_number": 0,
      "name": "ดอก",
      "uom_name": "ดอก"
    },
    {
      "docstatus": 0,
      "doctype": "UOM",
      "enabled": 1,
      "modified": "2025-02-15 18:43:30.034046",
      "must_be_whole_number": 0,
      "name": "แผง",
      "uom_name": "แผง"
    },
    {
      "docstatus": 0,
      "doctype": "UOM",
      "enabled": 1,
      "modified": "2025-02-15 18:43:30.034046",
      "must_be_whole_number": 0,
      "name": "ตลับ",
      "uom_name": "ตลับ"
    },
    {
      "docstatus": 0,
      "doctype": "UOM",
      "enabled": 1,
      "modified": "2025-02-15 18:43:30.034046",
      "must_be_whole_number": 0,
      "name": "เที่ยว",
      "uom_name": "เที่ยว"
    },
    {
      "docstatus": 0,
      "doctype": "UOM",
      "enabled": 1,
      "modified": "2025-02-15 18:43:30.034046",
      "must_be_whole_number": 0,
      "name": "ตัว",
      "uom_name": "ตัว"
    },
    {
      "docstatus": 0,
      "doctype": "UOM",
      "enabled": 1,
      "modified": "2025-02-15 18:43:30.034046",
      "must_be_whole_number": 0,
      "name": "นัด",
      "uom_name": "นัด"
    },
    {
      "docstatus": 0,
      "doctype": "UOM",
      "enabled": 1,
      "modified": "2025-02-15 18:43:30.034046",
      "must_be_whole_number": 0,
      "name": "แท่น",
      "uom_name": "แท่น"
    },
    {
      "docstatus": 0,
      "doctype": "UOM",
      "enabled": 1,
      "modified": "2025-02-15 18:43:30.034046",
      "must_be_whole_number": 0,
      "name": "บาน",
      "uom_name": "บาน"
    },
    {
      "docstatus": 0,
      "doctype": "UOM",
      "enabled": 1,
      "modified": "2025-02-15 18:43:30.034046",
      "must_be_whole_number": 0,
      "name": "ใบ",
      "uom_name": "ใบ"
    },
    {
      "docstatus": 0,
      "doctype": "UOM",
      "enabled": 1,
      "modified": "2025-02-15 18:43:30.034046",
      "must_be_whole_number": 0,
      "name": "ภาพ/รูป",
      "uom_name": "ภาพ/รูป"
    },
    {
      "docstatus": 0,
      "doctype": "UOM",
      "enabled": 1,
      "modified": "2025-02-15 18:43:30.034046",
      "must_be_whole_number": 0,
      "name": "เรือน",
      "uom_name": "เรือน"
    },
    {
      "docstatus": 0,
      "doctype": "UOM",
      "enabled": 1,
      "modified": "2025-02-15 18:43:30.034046",
      "must_be_whole_number": 0,
      "name": "ล้อ",
      "uom_name": "ล้อ"
    },
    {
      "docstatus": 0,
      "doctype": "UOM",
      "enabled": 1,
      "modified": "2025-02-15 18:43:30.034046",
      "must_be_whole_number": 0,
      "name": "ลัง",
      "uom_name": "ลัง"
    },
    {
      "docstatus": 0,
      "doctype": "UOM",
      "enabled": 1,
      "modified": "2025-02-15 18:43:30.034046",
      "must_be_whole_number": 0,
      "name": "วง",
      "uom_name": "วง"
    },
    {
      "docstatus": 0,
      "doctype": "UOM",
      "enabled": 1,
      "modified": "2025-02-15 18:43:30.034046",
      "must_be_whole_number": 0,
      "name": "เส้น",
      "uom_name": "เส้น"
    },
    {
      "docstatus": 0,
      "doctype": "UOM",
      "enabled": 1,
      "modified": "2025-02-15 18:43:30.034046",
      "must_be_whole_number": 0,
      "name": "ลูก",
      "uom_name": "ลูก"
    },
    {
      "docstatus": 0,
      "doctype": "UOM",
      "enabled": 1,
      "modified": "2025-02-15 18:43:30.034046",
      "must_be_whole_number": 0,
      "name": "หลอด",
      "uom_name": "หลอด"
    },
    {
      "docstatus": 0,
      "doctype": "UOM",
      "enabled": 1,
      "modified": "2025-02-15 18:43:30.034046",
      "must_be_whole_number": 0,
      "name": "หลัง",
      "uom_name": "หลัง"
    },
    {
      "docstatus": 0,
      "doctype": "UOM",
      "enabled": 1,
      "modified": "2025-02-15 18:43:30.034046",
      "must_be_whole_number": 0,
      "name": "เม็ด",
      "uom_name": "เม็ด"
    },
    {
      "docstatus": 0,
      "doctype": "UOM",
      "enabled": 1,
      "modified": "2025-02-15 18:43:30.034046",
      "must_be_whole_number": 0,
      "name": "ไมโครแอมแปร์",
      "uom_name": "ไมโครแอมแปร์"
    },
    {
      "docstatus": 0,
      "doctype": "UOM",
      "enabled": 1,
      "modified": "2025-02-15 18:43:30.034046",
      "must_be_whole_number": 0,
      "name": "ไมโครฟาเรด",
      "uom_name": "ไมโครฟาเรด"
    },
    {
      "docstatus": 0,
      "doctype": "UOM",
      "enabled": 1,
      "modified": "2025-02-15 18:43:30.034046",
      "must_be_whole_number": 0,
      "name": "ไมโครเมตร",
      "uom_name": "ไมโครเมตร"
    },
    {
      "docstatus": 0,
      "doctype": "UOM",
      "enabled": 1,
      "modified": "2025-02-15 18:43:30.034046",
      "must_be_whole_number": 0,
      "name": "ไมโครกรัม/ลูกบาศก์เมตร",
      "uom_name": "ไมโครกรัม/ลูกบาศก์เมตร"
    },
    {
      "docstatus": 0,
      "doctype": "UOM",
      "enabled": 1,
      "modified": "2025-02-15 18:43:30.034046",
      "must_be_whole_number": 0,
      "name": "ไมโครลิตร",
      "uom_name": "ไมโครลิตร"
    },
    {
      "docstatus": 0,
      "doctype": "UOM",
      "enabled": 1,
      "modified": "2025-02-15 18:43:30.034046",
      "must_be_whole_number": 0,
      "name": "กระสอบ",
      "uom_name": "กระสอบ"
    },
    {
      "docstatus": 0,
      "doctype": "UOM",
      "enabled": 1,
      "modified": "2025-02-15 18:43:30.034046",
      "must_be_whole_number": 0,
      "name": "ไมโครกรัม/ลิตร",
      "uom_name": "ไมโครกรัม/ลิตร"
    },
    {
      "docstatus": 0,
      "doctype": "UOM",
      "enabled": 1,
      "modified": "2025-02-15 18:43:30.034046",
      "must_be_whole_number": 0,
      "name": "กรง",
      "uom_name": "กรง"
    },
    {
      "docstatus": 0,
      "doctype": "UOM",
      "enabled": 1,
      "modified": "2025-02-15 18:43:30.034046",
      "must_be_whole_number": 0,
      "name": "กรอบ",
      "uom_name": "กรอบ"
    },
    {
      "docstatus": 0,
      "doctype": "UOM",
      "enabled": 1,
      "modified": "2025-02-15 18:43:30.034046",
      "must_be_whole_number": 0,
      "name": "กระถาง",
      "uom_name": "กระถาง"
    },
    {
      "docstatus": 0,
      "doctype": "UOM",
      "enabled": 1,
      "modified": "2025-02-15 18:43:30.034046",
      "must_be_whole_number": 0,
      "name": "กระบอก",
      "uom_name": "กระบอก"
    },
    {
      "docstatus": 0,
      "doctype": "UOM",
      "enabled": 1,
      "modified": "2025-02-15 18:43:30.034046",
      "must_be_whole_number": 0,
      "name": "ก้อน",
      "uom_name": "ก้อน"
    },
    {
      "docstatus": 0,
      "doctype": "UOM",
      "enabled": 1,
      "modified": "2025-02-15 18:43:30.034046",
      "must_be_whole_number": 0,
      "name": "หน่วย",
      "uom_name": "หน่วย"
    },
    {
      "docstatus": 0,
      "doctype": "UOM",
      "enabled": 1,
      "modified": "2025-02-15 18:43:30.034046",
      "must_be_whole_number": 0,
      "name": "วัสดุที่คิดมูลค่าเท่านั้น",
      "uom_name": "วัสดุที่คิดมูลค่าเท่านั้น"
    },
    {
      "docstatus": 0,
      "doctype": "UOM",
      "enabled": 1,
      "modified": "2025-02-15 18:43:30.034046",
      "must_be_whole_number": 0,
      "name": "โวลต์แอมแปร์",
      "uom_name": "โวลต์แอมแปร์"
    },
    {
      "docstatus": 0,
      "doctype": "UOM",
      "enabled": 1,
      "modified": "2025-02-15 18:43:30.034046",
      "must_be_whole_number": 0,
      "name": "สัปดาห์",
      "uom_name": "สัปดาห์"
    },
    {
      "docstatus": 0,
      "doctype": "UOM",
      "enabled": 1,
      "modified": "2025-02-15 18:43:30.034046",
      "must_be_whole_number": 0,
      "name": "ปี",
      "uom_name": "ปี"
    },
    {
      "docstatus": 0,
      "doctype": "UOM",
      "enabled": 1,
      "modified": "2025-02-15 18:43:30.034046",
      "must_be_whole_number": 0,
      "name": "หลา",
      "uom_name": "หลา"
    },
    {
      "docstatus": 0,
      "doctype": "UOM",
      "enabled": 1,
      "modified": "2025-02-15 18:43:30.034046",
      "must_be_whole_number": 0,
      "name": "ตารางหลา",
      "uom_name": "ตารางหลา"
    },
    {
      "docstatus": 0,
      "doctype": "UOM",
      "enabled": 1,
      "modified": "2025-02-15 18:43:30.034046",
      "must_be_whole_number": 0,
      "name": "ลูกบาศก์หลา",
      "uom_name": "ลูกบาศก์หลา"
    }
    ]
    